huaweicloudsdkcloudtable/__init__.py
huaweicloudsdkcloudtable/v2/__init__.py
huaweicloudsdkcloudtable/v2/cloudtable_async_client.py
huaweicloudsdkcloudtable/v2/cloudtable_client.py
huaweicloudsdkcloudtable/v2/model/__init__.py
huaweicloudsdkcloudtable/v2/model/action_progress.py
huaweicloudsdkcloudtable/v2/model/add_component_req.py
huaweicloudsdkcloudtable/v2/model/cluster.py
huaweicloudsdkcloudtable/v2/model/cluster_detail.py
huaweicloudsdkcloudtable/v2/model/create_cloud_table_cluster_request.py
huaweicloudsdkcloudtable/v2/model/create_cloud_table_cluster_response.py
huaweicloudsdkcloudtable/v2/model/create_cluster_instance_body.py
huaweicloudsdkcloudtable/v2/model/create_cluster_req_body.py
huaweicloudsdkcloudtable/v2/model/create_cluster_req_body_cluster_info.py
huaweicloudsdkcloudtable/v2/model/create_cluster_request.py
huaweicloudsdkcloudtable/v2/model/create_cluster_request_body.py
huaweicloudsdkcloudtable/v2/model/create_cluster_response.py
huaweicloudsdkcloudtable/v2/model/datastore.py
huaweicloudsdkcloudtable/v2/model/delete_cluster_request.py
huaweicloudsdkcloudtable/v2/model/delete_cluster_response.py
huaweicloudsdkcloudtable/v2/model/enable_component_request.py
huaweicloudsdkcloudtable/v2/model/enable_component_response.py
huaweicloudsdkcloudtable/v2/model/expand_cluster_component_request.py
huaweicloudsdkcloudtable/v2/model/expand_cluster_component_response.py
huaweicloudsdkcloudtable/v2/model/grow_node_req.py
huaweicloudsdkcloudtable/v2/model/hbase_cluster_action_req.py
huaweicloudsdkcloudtable/v2/model/hbase_modify_setting_v2.py
huaweicloudsdkcloudtable/v2/model/hbase_modify_setting_v2_req.py
huaweicloudsdkcloudtable/v2/model/instance.py
huaweicloudsdkcloudtable/v2/model/list_clusters_request.py
huaweicloudsdkcloudtable/v2/model/list_clusters_response.py
huaweicloudsdkcloudtable/v2/model/nic.py
huaweicloudsdkcloudtable/v2/model/parameter_info.py
huaweicloudsdkcloudtable/v2/model/reboot_cloud_table_cluster_request.py
huaweicloudsdkcloudtable-3.1.184.dist-info/METADATA
huaweicloudsdkcloudtable-3.1.184.dist-info/WHEEL
huaweicloudsdkcloudtable-3.1.184.dist-info/licenses/LICENSE
huaweicloudsdkcloudtable-3.1.184.dist-info/RECORD
